{
  "bbbs": "2c909fdd678bf17901678bf70bc70587",
  "title": "中华人民共和国著作权法",
  "gbrq": "2010-02-26",
  "sxrq": "2010-04-01",
  "sxx": 2,
  "zdjgName": "全国人民代表大会常务委员会",
  "flxz": "法律",
  "zdjgCodeId": 110,
  "flfgCodeId": 120,
  "detail": {
    "bbbs": "2c909fdd678bf17901678bf70bc70587",
    "ossFile": {
      "ossWordPath": "prod/20100226/9dbd99448ee44bab9efe34ca8d1c9560.docx",
      "ossWordOfdPath": "prod/20100226/9dbd99448ee44bab9efe34ca8d1c9560.ofd",
      "ossWordOfdSize": 179028,
      "ossPdfPath": "prod/20100226/7132244e25e54a2b8f215dfc087331d3.pdf",
      "ossPdfOfdPath": "prod/20100226/7132244e25e54a2b8f215dfc087331d3.ofd",
      "ossPdfOfdSize": 5387991
    },
    "xgwj": [],
    "lsyg": [
      {
        "bbbs": "ff808081752b7d430175e4766bab1557",
        "title": "中华人民共和国著作权法",
        "gbrq": "2020-11-11",
        "highLight": false
      },
      {
        "bbbs": "2c909fdd678bf17901678bf70bc70587",
        "title": "中华人民共和国著作权法",
        "gbrq": "2010-02-26",
        "highLight": true
      }
    ],
    "xgzl": [],
    "flfg": null,
    "flxz": "法律",
    "zdjgName": "全国人民代表大会常务委员会",
    "gbrq": "2010-02-26",
    "sxrq": "2010-04-01",
    "title": "中华人民共和国著作权法",
    "sxx": 2,
    "content": {
      "id": "79890000-3e3b-0016-abe8-08dd684cdb38",
      "parentId": "00000000-0000-0000-0000-000000000000",
      "title": "中华人民共和国著作权法",
      "index": 0,
      "children": [
        {
          "id": "79890000-3e3b-0016-ac7c-08dd684cdb38",
          "parentId": "79890000-3e3b-0016-abe8-08dd684cdb38",
          "title": "题注",
          "index": 1,
          "children": []
        },
        {
          "id": "79890000-3e3b-0016-ace6-08dd684cdb38",
          "parentId": "79890000-3e3b-0016-abe8-08dd684cdb38",
          "title": "目录",
          "index": 2,
          "children": []
        },
        {
          "id": "79890000-3e3b-0016-bfbc-08dd684cdb38",
          "parentId": "79890000-3e3b-0016-abe8-08dd684cdb38",
          "title": "第一章 总则",
          "index": 3,
          "children": [
            {
              "id": "79890000-3e3b-0016-d0f7-08dd684cdb38",
              "parentId": "79890000-3e3b-0016-bfbc-08dd684cdb38",
              "title": "第一条",
              "index": 4,
              "children": []
            },
            {
              "id": "79890000-3e3b-0016-e265-08dd684cdb38",
              "parentId": "79890000-3e3b-0016-bfbc-08dd684cdb38",
              "title": "第二条",
              "index": 5,
              "children": []
            },
            {
              "id": "79890000-3e3b-0016-f428-08dd684cdb38",
              "parentId": "79890000-3e3b-0016-bfbc-08dd684cdb38",
              "title": "第三条",
              "index": 6,
              "children": []
            },
            {
              "id": "79890000-3e3b-0016-07bb-08dd684cdb39",
              "parentId": "79890000-3e3b-0016-bfbc-08dd684cdb38",
              "title": "第四条",
              "index": 7,
              "children": []
            },
            {
              "id": "79890000-3e3b-0016-185b-08dd684cdb39",
              "parentId": "79890000-3e3b-0016-bfbc-08dd684cdb38",
              "title": "第五条",
              "index": 8,
              "children": []
            },
            {
              "id": "79890000-3e3b-0016-29a4-08dd684cdb39",
              "parentId": "79890000-3e3b-0016-bfbc-08dd684cdb38",
              "title": "第六条",
              "index": 9,
              "children": []
            },
            {
              "id": "79890000-3e3b-0016-39e5-08dd684cdb39",
              "parentId": "79890000-3e3b-0016-bfbc-08dd684cdb38",
              "title": "第七条",
              "index": 10,
              "children": []
            },
            {
              "id": "79890000-3e3b-0016-4a90-08dd684cdb39",
              "parentId": "79890000-3e3b-0016-bfbc-08dd684cdb38",
              "title": "第八条",
              "index": 11,
              "children": []
            }
          ]
        },
        {
          "id": "79890000-3e3b-0016-5acd-08dd684cdb39",
          "parentId": "79890000-3e3b-0016-abe8-08dd684cdb38",
          "title": "第二章 著作权",
          "index": 12,
          "children": [
            {
              "id": "79890000-3e3b-0016-6aa7-08dd684cdb39",
              "parentId": "79890000-3e3b-0016-5acd-08dd684cdb39",
              "title": "第一节 著作权人及其权利",
              "index": 13,
              "children": [
                {
                  "id": "79890000-3e3b-0016-7a78-08dd684cdb39",
                  "parentId": "79890000-3e3b-0016-6aa7-08dd684cdb39",
                  "title": "第九条",
                  "index": 14,
                  "children": []
                },
                {
                  "id": "79890000-3e3b-0016-8bf0-08dd684cdb39",
                  "parentId": "79890000-3e3b-0016-6aa7-08dd684cdb39",
                  "title": "第十条",
                  "index": 15,
                  "children": []
                }
              ]
            },
            {
              "id": "79890000-3e3b-0016-a0a6-08dd684cdb39",
              "parentId": "79890000-3e3b-0016-5acd-08dd684cdb39",
              "title": "第二节 著作权归属",
              "index": 16,
              "children": [
                {
                  "id": "79890000-3e3b-0016-b82e-08dd684cdb39",
                  "parentId": "79890000-3e3b-0016-a0a6-08dd684cdb39",
                  "title": "第十一条",
                  "index": 17,
                  "children": []
                },
                {
                  "id": "79890000-3e3b-0016-cbf3-08dd684cdb39",
                  "parentId": "79890000-3e3b-0016-a0a6-08dd684cdb39",
                  "title": "第十二条",
                  "index": 18,
                  "children": []
                },
                {
                  "id": "79890000-3e3b-0016-df12-08dd684cdb39",
                  "parentId": "79890000-3e3b-0016-a0a6-08dd684cdb39",
                  "title": "第十三条",
                  "index": 19,
                  "children": []
                },
                {
                  "id": "79890000-3e3b-0016-f0a4-08dd684cdb39",
                  "parentId": "79890000-3e3b-0016-a0a6-08dd684cdb39",
                  "title": "第十四条",
                  "index": 20,
                  "children": []
                },
                {
                  "id": "79890000-3e3b-0016-032a-08dd684cdb3a",
                  "parentId": "79890000-3e3b-0016-a0a6-08dd684cdb39",
                  "title": "第十五条",
                  "index": 21,
                  "children": []
                },
                {
                  "id": "79890000-3e3b-0016-15fd-08dd684cdb3a",
                  "parentId": "79890000-3e3b-0016-a0a6-08dd684cdb39",
                  "title": "第十六条",
                  "index": 22,
                  "children": []
                },
                {
                  "id": "79890000-3e3b-0016-293f-08dd684cdb3a",
                  "parentId": "79890000-3e3b-0016-a0a6-08dd684cdb39",
                  "title": "第十七条",
                  "index": 23,
                  "children": []
                },
                {
                  "id": "79890000-3e3b-0016-3c21-08dd684cdb3a",
                  "parentId": "79890000-3e3b-0016-a0a6-08dd684cdb39",
                  "title": "第十八条",
                  "index": 24,
                  "children": []
                },
                {
                  "id": "79890000-3e3b-0016-4ed0-08dd684cdb3a",
                  "parentId": "79890000-3e3b-0016-a0a6-08dd684cdb39",
                  "title": "第十九条",
                  "index": 25,
                  "children": []
                }
              ]
            },
            {
              "id": "79890000-3e3b-0016-618e-08dd684cdb3a",
              "parentId": "79890000-3e3b-0016-5acd-08dd684cdb39",
              "title": "第三节 权利的保护期",
              "index": 26,
              "children": [
                {
                  "id": "79890000-3e3b-0016-73d9-08dd684cdb3a",
                  "parentId": "79890000-3e3b-0016-618e-08dd684cdb3a",
                  "title": "第二十条",
                  "index": 27,
                  "children": []
                },
                {
                  "id": "79890000-3e3b-0016-870c-08dd684cdb3a",
                  "parentId": "79890000-3e3b-0016-618e-08dd684cdb3a",
                  "title": "第二十一条",
                  "index": 28,
                  "children": []
                }
              ]
            },
            {
              "id": "79890000-3e3b-0016-9a0d-08dd684cdb3a",
              "parentId": "79890000-3e3b-0016-5acd-08dd684cdb39",
              "title": "第四节 权利的限制",
              "index": 29,
              "children": [
                {
                  "id": "79890000-3e3b-0016-acfb-08dd684cdb3a",
                  "parentId": "79890000-3e3b-0016-9a0d-08dd684cdb3a",
                  "title": "第二十二条",
                  "index": 30,
                  "children": []
                },
                {
                  "id": "79890000-3e3b-0016-c34e-08dd684cdb3a",
                  "parentId": "79890000-3e3b-0016-9a0d-08dd684cdb3a",
                  "title": "第二十三条",
                  "index": 31,
                  "children": []
                }
              ]
            }
          ]
        },
        {
          "id": "79890000-3e3b-0016-d6db-08dd684cdb3a",
          "parentId": "79890000-3e3b-0016-abe8-08dd684cdb38",
          "title": "第三章 著作权许可使用和转让合同",
          "index": 32,
          "children": [
            {
              "id": "79890000-3e3b-0016-e9c9-08dd684cdb3a",
              "parentId": "79890000-3e3b-0016-d6db-08dd684cdb3a",
              "title": "第二十四条",
              "index": 33,
              "children": []
            },
            {
              "id": "79890000-3e3b-0016-045c-08dd684cdb3b",
              "parentId": "79890000-3e3b-0016-d6db-08dd684cdb3a",
              "title": "第二十五条",
              "index": 34,
              "children": []
            },
            {
              "id": "79890000-3e3b-0016-1ac1-08dd684cdb3b",
              "parentId": "79890000-3e3b-0016-d6db-08dd684cdb3a",
              "title": "第二十六条",
              "index": 35,
              "children": []
            },
            {
              "id": "79890000-3e3b-0016-2e9f-08dd684cdb3b",
              "parentId": "79890000-3e3b-0016-d6db-08dd684cdb3a",
              "title": "第二十七条",
              "index": 36,
              "children": []
            },
            {
              "id": "79890000-3e3b-0016-4270-08dd684cdb3b",
              "parentId": "79890000-3e3b-0016-d6db-08dd684cdb3a",
              "title": "第二十八条",
              "index": 37,
              "children": []
            },
            {
              "id": "79890000-3e3b-0016-55da-08dd684cdb3b",
              "parentId": "79890000-3e3b-0016-d6db-08dd684cdb3a",
              "title": "第二十九条",
              "index": 38,
              "children": []
            }
          ]
        },
        {
          "id": "79890000-3e3b-0016-699f-08dd684cdb3b",
          "parentId": "79890000-3e3b-0016-abe8-08dd684cdb38",
          "title": "第四章 出版、表演、录音录像、播放",
          "index": 39,
          "children": [
            {
              "id": "79890000-3e3b-0016-7c5d-08dd684cdb3b",
              "parentId": "79890000-3e3b-0016-699f-08dd684cdb3b",
              "title": "第一节 图书、报刊的出版",
              "index": 40,
              "children": [
                {
                  "id": "79890000-3e3b-0016-8eef-08dd684cdb3b",
                  "parentId": "79890000-3e3b-0016-7c5d-08dd684cdb3b",
                  "title": "第三十条",
                  "index": 41,
                  "children": []
                },
                {
                  "id": "79890000-3e3b-0016-a154-08dd684cdb3b",
                  "parentId": "79890000-3e3b-0016-7c5d-08dd684cdb3b",
                  "title": "第三十一条",
                  "index": 42,
                  "children": []
                },
                {
                  "id": "79890000-3e3b-0016-b43d-08dd684cdb3b",
                  "parentId": "79890000-3e3b-0016-7c5d-08dd684cdb3b",
                  "title": "第三十二条",
                  "index": 43,
                  "children": []
                },
                {
                  "id": "79890000-3e3b-0016-c740-08dd684cdb3b",
                  "parentId": "79890000-3e3b-0016-7c5d-08dd684cdb3b",
                  "title": "第三十三条",
                  "index": 44,
                  "children": []
                },
                {
                  "id": "79890000-3e3b-0016-da85-08dd684cdb3b",
                  "parentId": "79890000-3e3b-0016-7c5d-08dd684cdb3b",
                  "title": "第三十四条",
                  "index": 45,
                  "children": []
                },
                {
                  "id": "79890000-3e3b-0016-ed5a-08dd684cdb3b",
                  "parentId": "79890000-3e3b-0016-7c5d-08dd684cdb3b",
                  "title": "第三十五条",
                  "index": 46,
                  "children": []
                },
                {
                  "id": "79890000-3e3b-0016-0031-08dd684cdb3c",
                  "parentId": "79890000-3e3b-0016-7c5d-08dd684cdb3b",
                  "title": "第三十六条",
                  "index": 47,
                  "children": []
                }
              ]
            },
            {
              "id": "79890000-3e3b-0016-2497-08dd684cdb3c",
              "parentId": "79890000-3e3b-0016-699f-08dd684cdb3b",
              "title": "第二节 表演",
              "index": 48,
              "children": [
                {
                  "id": "79890000-3e3b-0016-4334-08dd684cdb3c",
                  "parentId": "79890000-3e3b-0016-2497-08dd684cdb3c",
                  "title": "第三十七条",
                  "index": 49,
                  "children": []
                },
                {
                  "id": "79890000-3e3b-0016-5f7c-08dd684cdb3c",
                  "parentId": "79890000-3e3b-0016-2497-08dd684cdb3c",
                  "title": "第三十八条",
                  "index": 50,
                  "children": []
                },
                {
                  "id": "79890000-3e3b-0016-7efe-08dd684cdb3c",
                  "parentId": "79890000-3e3b-0016-2497-08dd684cdb3c",
                  "title": "第三十九条",
                  "index": 51,
                  "children": []
                }
              ]
            },
            {
              "id": "79890000-3e3b-0016-9a2b-08dd684cdb3c",
              "parentId": "79890000-3e3b-0016-699f-08dd684cdb3b",
              "title": "第三节 录音录像",
              "index": 52,
              "children": [
                {
                  "id": "79890000-3e3b-0016-b3a4-08dd684cdb3c",
                  "parentId": "79890000-3e3b-0016-9a2b-08dd684cdb3c",
                  "title": "第四十条",
                  "index": 53,
                  "children": []
                },
                {
                  "id": "79890000-3e3b-0016-cae2-08dd684cdb3c",
                  "parentId": "79890000-3e3b-0016-9a2b-08dd684cdb3c",
                  "title": "第四十一条",
                  "index": 54,
                  "children": []
                },
                {
                  "id": "79890000-3e3b-0016-fc72-08dd684cdb3c",
                  "parentId": "79890000-3e3b-0016-9a2b-08dd684cdb3c",
                  "title": "第四十二条",
                  "index": 55,
                  "children": []
                }
              ]
            },
            {
              "id": "79890000-3e3b-0016-1062-08dd684cdb3d",
              "parentId": "79890000-3e3b-0016-699f-08dd684cdb3b",
              "title": "第四节 广播电台、电视台播放",
              "index": 56,
              "children": [
                {
                  "id": "79890000-3e3b-0016-240b-08dd684cdb3d",
                  "parentId": "79890000-3e3b-0016-1062-08dd684cdb3d",
                  "title": "第四十三条",
                  "index": 57,
                  "children": []
                },
                {
                  "id": "79890000-3e3b-0016-3816-08dd684cdb3d",
                  "parentId": "79890000-3e3b-0016-1062-08dd684cdb3d",
                  "title": "第四十四条",
                  "index": 58,
                  "children": []
                },
                {
                  "id": "79890000-3e3b-0016-4bf2-08dd684cdb3d",
                  "parentId": "79890000-3e3b-0016-1062-08dd684cdb3d",
                  "title": "第四十五条",
                  "index": 59,
                  "children": []
                },
                {
                  "id": "79890000-3e3b-0016-611e-08dd684cdb3d",
                  "parentId": "79890000-3e3b-0016-1062-08dd684cdb3d",
                  "title": "第四十六条",
                  "index": 60,
                  "children": []
                }
              ]
            }
          ]
        },
        {
          "id": "79890000-3e3b-0016-7558-08dd684cdb3d",
          "parentId": "79890000-3e3b-0016-abe8-08dd684cdb38",
          "title": "第五章 法律责任和执法措施",
          "index": 61,
          "children": [
            {
              "id": "79890000-3e3b-0016-894c-08dd684cdb3d",
              "parentId": "79890000-3e3b-0016-7558-08dd684cdb3d",
              "title": "第四十七条",
              "index": 62,
              "children": []
            },
            {
              "id": "79890000-3e3b-0016-a049-08dd684cdb3d",
              "parentId": "79890000-3e3b-0016-7558-08dd684cdb3d",
              "title": "第四十八条",
              "index": 63,
              "children": []
            },
            {
              "id": "79890000-3e3b-0016-b6bd-08dd684cdb3d",
              "parentId": "79890000-3e3b-0016-7558-08dd684cdb3d",
              "title": "第四十九条",
              "index": 64,
              "children": []
            },
            {
              "id": "79890000-3e3b-0016-cb8d-08dd684cdb3d",
              "parentId": "79890000-3e3b-0016-7558-08dd684cdb3d",
              "title": "第五十条",
              "index": 65,
              "children": []
            },
            {
              "id": "79890000-3e3b-0016-fdcc-08dd684cdb3d",
              "parentId": "79890000-3e3b-0016-7558-08dd684cdb3d",
              "title": "第五十一条",
              "index": 66,
              "children": []
            },
            {
              "id": "79890000-3e3b-0016-1543-08dd684cdb3e",
              "parentId": "79890000-3e3b-0016-7558-08dd684cdb3d",
              "title": "第五十二条",
              "index": 67,
              "children": []
            },
            {
              "id": "79890000-3e3b-0016-2b7d-08dd684cdb3e",
              "parentId": "79890000-3e3b-0016-7558-08dd684cdb3d",
              "title": "第五十三条",
              "index": 68,
              "children": []
            },
            {
              "id": "79890000-3e3b-0016-402a-08dd684cdb3e",
              "parentId": "79890000-3e3b-0016-7558-08dd684cdb3d",
              "title": "第五十四条",
              "index": 69,
              "children": []
            },
            {
              "id": "79890000-3e3b-0016-5547-08dd684cdb3e",
              "parentId": "79890000-3e3b-0016-7558-08dd684cdb3d",
              "title": "第五十五条",
              "index": 70,
              "children": []
            },
            {
              "id": "79890000-3e3b-0016-6a08-08dd684cdb3e",
              "parentId": "79890000-3e3b-0016-7558-08dd684cdb3d",
              "title": "第五十六条",
              "index": 71,
              "children": []
            }
          ]
        },
        {
          "id": "79890000-3e3b-0016-83cd-08dd684cdb3e",
          "parentId": "79890000-3e3b-0016-abe8-08dd684cdb38",
          "title": "第六章 附则",
          "index": 72,
          "children": [
            {
              "id": "79890000-3e3b-0016-99e1-08dd684cdb3e",
              "parentId": "79890000-3e3b-0016-83cd-08dd684cdb3e",
              "title": "第五十七条",
              "index": 73,
              "children": []
            },
            {
              "id": "79890000-3e3b-0016-af8c-08dd684cdb3e",
              "parentId": "79890000-3e3b-0016-83cd-08dd684cdb3e",
              "title": "第五十八条",
              "index": 74,
              "children": []
            },
            {
              "id": "79890000-3e3b-0016-c52f-08dd684cdb3e",
              "parentId": "79890000-3e3b-0016-83cd-08dd684cdb3e",
              "title": "第五十九条",
              "index": 75,
              "children": []
            },
            {
              "id": "79890000-3e3b-0016-da4b-08dd684cdb3e",
              "parentId": "79890000-3e3b-0016-83cd-08dd684cdb3e",
              "title": "第六十条",
              "index": 76,
              "children": []
            },
            {
              "id": "79890000-3e3b-0016-efbb-08dd684cdb3e",
              "parentId": "79890000-3e3b-0016-83cd-08dd684cdb3e",
              "title": "第六十一条",
              "index": 77,
              "children": []
            }
          ]
        }
      ]
    },
    "xfFlag": 0
  },
  "fetch_time": "2026-03-10 23:45:18"
}