{
  "bbbs": "ff808181865edc140186d9d8aef52506",
  "title": "全国人民代表大会关于修改《中华人民共和国立法法》的决定",
  "gbrq": "2023-03-13",
  "sxrq": "2023-03-15",
  "sxx": null,
  "zdjgName": "全国人民代表大会",
  "flxz": "修改、废止的决定",
  "zdjgCodeId": 100,
  "flfgCodeId": 200,
  "detail": {
    "bbbs": "ff808181865edc140186d9d8aef52506",
    "ossFile": {
      "ossWordPath": "prod/20230313/b99da065e72b4076b2d08b7a664f59d3.docx",
      "ossWordOfdPath": "prod/20230313/b99da065e72b4076b2d08b7a664f59d3.ofd",
      "ossWordOfdSize": 120404,
      "ossPdfPath": "prod/20230313/6ed125f2bb70404dbc7c3472a158dd50.pdf",
      "ossPdfOfdPath": "prod/20230313/6ed125f2bb70404dbc7c3472a158dd50.ofd",
      "ossPdfOfdSize": 1086887
    },
    "xgwj": [],
    "lsyg": null,
    "xgzl": [],
    "flfg": [
      {
        "bbbs": "2c909fdd678bf17901678bf783fc0767",
        "title": "中华人民共和国立法法"
      }
    ],
    "flxz": "修改、废止的决定",
    "zdjgName": "全国人民代表大会",
    "gbrq": "2023-03-13",
    "sxrq": "2023-03-15",
    "title": "全国人民代表大会关于修改《中华人民共和国立法法》的决定",
    "sxx": null,
    "content": null,
    "xfFlag": 0
  },
  "fetch_time": "2026-03-10 23:29:10"
}