{
  "bbbs": "ff808081774c7a3d01777172228b1e5a",
  "title": "全国人民代表大会关于授权国务院在经济体制改革和对外开放方面可以制定暂行的规定或者条例的决定",
  "gbrq": null,
  "sxrq": "1985-04-10",
  "sxx": null,
  "zdjgName": "全国人民代表大会",
  "flxz": "有关法律问题和重大问题的决定（部分）",
  "zdjgCodeId": 100,
  "flfgCodeId": 190,
  "detail": {
    "bbbs": "ff808081774c7a3d01777172228b1e5a",
    "ossFile": {
      "ossWordPath": "prod/19700101/b4d638c6ce49420691ab82d1c7b8ab2f.docx",
      "ossWordOfdPath": "prod/19700101/b4d638c6ce49420691ab82d1c7b8ab2f.ofd",
      "ossWordOfdSize": 30390,
      "ossPdfPath": "prod/19700101/d8e0feffdfaf4741a9a2e0ed330bd643.pdf",
      "ossPdfOfdPath": "prod/19700101/d8e0feffdfaf4741a9a2e0ed330bd643.ofd",
      "ossPdfOfdSize": 288353
    },
    "xgwj": [],
    "lsyg": null,
    "xgzl": [],
    "flfg": null,
    "flxz": "有关法律问题和重大问题的决定（部分）",
    "zdjgName": "全国人民代表大会",
    "gbrq": null,
    "sxrq": "1985-04-10",
    "title": "全国人民代表大会关于授权国务院在经济体制改革和对外开放方面可以制定暂行的规定或者条例的决定",
    "sxx": null,
    "content": null,
    "xfFlag": 0
  },
  "fetch_time": "2026-03-10 23:59:15"
}