{
  "bbbs": "ff8081818c3ce0ed018cb649d1cb2ee4",
  "title": "全国人民代表大会常务委员会关于授权澳门特别行政区对广东省珠海市拱北口岸东南侧相关陆地和海域实施管辖的决定",
  "gbrq": "2023-12-29",
  "sxrq": null,
  "sxx": null,
  "zdjgName": "全国人民代表大会常务委员会",
  "flxz": "有关法律问题和重大问题的决定（部分）",
  "zdjgCodeId": 110,
  "flfgCodeId": 190,
  "detail": {
    "bbbs": "ff8081818c3ce0ed018cb649d1cb2ee4",
    "ossFile": {
      "ossWordPath": "prod/20231229/171dcebedd4f45c1a98636372af14a29.docx",
      "ossWordOfdPath": "prod/20231229/171dcebedd4f45c1a98636372af14a29.ofd",
      "ossWordOfdSize": 51091,
      "ossPdfPath": "prod/20231229/bea4a1dde5364b17a18ff0e3520be004.pdf",
      "ossPdfOfdPath": "prod/20231229/bea4a1dde5364b17a18ff0e3520be004.ofd",
      "ossPdfOfdSize": 748908
    },
    "xgwj": [],
    "lsyg": null,
    "xgzl": [
      {
        "fileId": "ff8081818d6a424b018e08d7661b1765",
        "title": "对《关于授权澳门特别行政区对广东省珠海市拱北口岸东南侧相关陆地和海域实施管辖的决定（草案）》的说明",
        "titleHighLight": null,
        "busiType": "草案的说明",
        "fileType": "docx",
        "titleHightLightList": null
      },
      {
        "fileId": "ff8081818d6a4639018e08d785cc16f7",
        "title": "对《关于授权澳门特别行政区对广东省珠海市拱北口岸东南侧相关陆地和海域实施管辖的决定（草案）》的说明",
        "titleHighLight": null,
        "busiType": "草案的说明",
        "fileType": "pdf",
        "titleHightLightList": null
      },
      {
        "fileId": "ff8081818d6a4639018e08d7b43f16fb",
        "title": "全国人民代表大会宪法和法律委员会关于《全国人民代表大会常务委员会关于授权澳门特别行政区对广东省珠海市拱北口岸东南侧相关陆地和海域实施管辖的决定（草案）》审议结果的报告",
        "titleHighLight": null,
        "busiType": "审议结果的报告",
        "fileType": "docx",
        "titleHightLightList": null
      },
      {
        "fileId": "ff8081818d6a4639018e08d7ea9e16fe",
        "title": "全国人民代表大会宪法和法律委员会关于《全国人民代表大会常务委员会关于授权澳门特别行政区对广东省珠海市拱北口岸东南侧相关陆地和海域实施管辖的决定（草案）》审议结果的报告",
        "titleHighLight": null,
        "busiType": "审议结果的报告",
        "fileType": "pdf",
        "titleHightLightList": null
      }
    ],
    "flfg": null,
    "flxz": "有关法律问题和重大问题的决定（部分）",
    "zdjgName": "全国人民代表大会常务委员会",
    "gbrq": "2023-12-29",
    "sxrq": null,
    "title": "全国人民代表大会常务委员会关于授权澳门特别行政区对广东省珠海市拱北口岸东南侧相关陆地和海域实施管辖的决定",
    "sxx": null,
    "content": null,
    "xfFlag": 0
  },
  "fetch_time": "2026-03-10 23:28:24"
}