{
  "bbbs": "ff808081774c7a3d0177716a15d11e36",
  "title": "全国人民代表大会常务委员会关于授权国务院对职工退休退职办法进行部分修改和补充的决定",
  "gbrq": null,
  "sxrq": "1983-09-02",
  "sxx": null,
  "zdjgName": "全国人民代表大会常务委员会",
  "flxz": "有关法律问题和重大问题的决定（部分）",
  "zdjgCodeId": 110,
  "flfgCodeId": 190,
  "detail": {
    "bbbs": "ff808081774c7a3d0177716a15d11e36",
    "ossFile": {
      "ossWordPath": "prod/19700101/3980461caee1409d80101bca72e2fb7c.docx",
      "ossWordOfdPath": "prod/19700101/3980461caee1409d80101bca72e2fb7c.ofd",
      "ossWordOfdSize": 21524,
      "ossPdfPath": "prod/19700101/2fd25b5d04444d409fe923d78ff37d90.pdf",
      "ossPdfOfdPath": "prod/19700101/2fd25b5d04444d409fe923d78ff37d90.ofd",
      "ossPdfOfdSize": 300138
    },
    "xgwj": [],
    "lsyg": null,
    "xgzl": [],
    "flfg": null,
    "flxz": "有关法律问题和重大问题的决定（部分）",
    "zdjgName": "全国人民代表大会常务委员会",
    "gbrq": null,
    "sxrq": "1983-09-02",
    "title": "全国人民代表大会常务委员会关于授权国务院对职工退休退职办法进行部分修改和补充的决定",
    "sxx": null,
    "content": null,
    "xfFlag": 0
  },
  "fetch_time": "2026-03-11 00:01:37"
}