{
  "bbbs": "ff808181865edc140186d8e286ee24a4",
  "title": "第十四届全国人民代表大会第一次会议关于第十四届全国人民代表大会专门委员会主任委员、副主任委员、委员人选的表决办法",
  "gbrq": "2023-03-05",
  "sxrq": "2023-03-05",
  "sxx": null,
  "zdjgName": "全国人民代表大会",
  "flxz": "有关法律问题和重大问题的决定（部分）",
  "zdjgCodeId": 100,
  "flfgCodeId": 190,
  "detail": {
    "bbbs": "ff808181865edc140186d8e286ee24a4",
    "ossFile": {
      "ossWordPath": "prod/20230305/1c73e051175b4d03b0f843ecf5ed9606.docx",
      "ossWordOfdPath": "prod/20230305/1c73e051175b4d03b0f843ecf5ed9606.ofd",
      "ossWordOfdSize": 41596,
      "ossPdfPath": "prod/20230305/8601c88171ca46a599d3b1dfc684aa42.pdf",
      "ossPdfOfdPath": "prod/20230305/8601c88171ca46a599d3b1dfc684aa42.ofd",
      "ossPdfOfdSize": 688175
    },
    "xgwj": [],
    "lsyg": null,
    "xgzl": [],
    "flfg": null,
    "flxz": "有关法律问题和重大问题的决定（部分）",
    "zdjgName": "全国人民代表大会",
    "gbrq": "2023-03-05",
    "sxrq": "2023-03-05",
    "title": "第十四届全国人民代表大会第一次会议关于第十四届全国人民代表大会专门委员会主任委员、副主任委员、委员人选的表决办法",
    "sxx": null,
    "content": null,
    "xfFlag": 0
  },
  "fetch_time": "2026-03-10 23:29:20"
}