{
  "bbbs": "402881e45ffb0c10015ffb300d4800d2",
  "title": "最高人民法院、最高人民检察院关于办理渎职刑事案件适用法律若干问题的解释（一）",
  "gbrq": "2012-12-07",
  "sxrq": "2013-01-09",
  "sxx": 3,
  "zdjgName": "最高人民法院、最高人民检察院",
  "flxz": "司法解释",
  "zdjgCodeId": 160,
  "flfgCodeId": 340,
  "detail": {
    "bbbs": "402881e45ffb0c10015ffb300d4800d2",
    "ossFile": {
      "ossWordPath": "prod/20121207/bd947ab8fa38482cb7f3d839956aac37.docx",
      "ossWordOfdPath": "prod/20121207/bd947ab8fa38482cb7f3d839956aac37.ofd",
      "ossWordOfdSize": 83698,
      "ossPdfPath": "prod/20121207/7185e6a47ca3485c8a1e9bae37b4c554.pdf",
      "ossPdfOfdPath": "prod/20121207/7185e6a47ca3485c8a1e9bae37b4c554.ofd",
      "ossPdfOfdSize": 3768960
    },
    "xgwj": [],
    "lsyg": null,
    "xgzl": [],
    "flfg": null,
    "flxz": "司法解释",
    "zdjgName": "最高人民法院、最高人民检察院",
    "gbrq": "2012-12-07",
    "sxrq": "2013-01-09",
    "title": "最高人民法院、最高人民检察院关于办理渎职刑事案件适用法律若干问题的解释（一）",
    "sxx": 3,
    "content": null,
    "xfFlag": 0
  },
  "fetch_time": "2026-03-11 08:30:38"
}