{
  "bbbs": "ff8080816f3cbb3c016f4125dd7719de",
  "title": "事业单位人事管理条例",
  "gbrq": "2014-04-25",
  "sxrq": "",
  "sxx": 3,
  "zdjgName": "国务院",
  "flxz": "行政法规",
  "zdjgCodeId": 120,
  "flfgCodeId": 210,
  "detail": {
    "bbbs": "ff8080816f3cbb3c016f4125dd7719de",
    "ossFile": {
      "ossWordPath": "prod/20140425/7a3d82275f464517ab34ceeff8bfcfb4.docx",
      "ossWordOfdPath": "prod/20140425/7a3d82275f464517ab34ceeff8bfcfb4.ofd",
      "ossWordOfdSize": 122564,
      "ossPdfPath": "prod/20140425/f5363d7b2fbe4af29fa2d4434c9576a4.pdf",
      "ossPdfOfdPath": "prod/20140425/f5363d7b2fbe4af29fa2d4434c9576a4.ofd",
      "ossPdfOfdSize": 2268961
    },
    "xgwj": [],
    "lsyg": null,
    "xgzl": [],
    "flfg": null,
    "flxz": "行政法规",
    "zdjgName": "国务院",
    "gbrq": "2014-04-25",
    "sxrq": null,
    "title": "事业单位人事管理条例",
    "sxx": 3,
    "content": null,
    "xfFlag": 0
  },
  "fetch_time": "2026-03-11 00:22:19"
}